simpleSynapse/__init__.py
simpleSynapse/command_line.py
simpleSynapse/pull.py
simpleSynapse/pull_cli.py
simpleSynapse/push.py
simpleSynapse/push_cli.py
simpleSynapse/run.py
simpleSynapse/simpleSynapse.py
simpleSynapse/simpleSynapsePull.py
simpleSynapse-0.4.dist-info/METADATA
simpleSynapse-0.4.dist-info/WHEEL
simpleSynapse-0.4.dist-info/entry_points.txt
simpleSynapse-0.4.dist-info/top_level.txt
simpleSynapse-0.4.dist-info/RECORD
